treeinterpreter/__init__.py
treeinterpreter/treeinterpreter.py
treeinterpreter/utils.py
treeinterpreter-0.2.2.dist-info/DESCRIPTION.rst
treeinterpreter-0.2.2.dist-info/METADATA
treeinterpreter-0.2.2.dist-info/RECORD
treeinterpreter-0.2.2.dist-info/WHEEL
treeinterpreter-0.2.2.dist-info/metadata.json
treeinterpreter-0.2.2.dist-info/top_level.txt
