Metadata-Version: 2.0
Name: treeinterpreter
Version: 0.2.2
Summary: Package for interpreting scikit-learn's decision tree and random forest predictions.
Home-page: https://github.com/andosa/treeinterpreter
Author: Ando Saabas
Author-email: UNKNOWN
License: BSD
Keywords: treeinterpreter
Platform: UNKNOWN
Classifier: License :: OSI Approved :: BSD License
Classifier: Natural Language :: English
Classifier: Programming Language :: Python
